.gitignore
MANIFEST.in
setup.py
ebs/__init__.py
ebs/linuxnode/__init__.py
ebs/linuxnode/gui/__init__.py
ebs/linuxnode/gui/kivy/__init__.py
ebs/linuxnode/gui/kivy/animations/__init__.py
ebs/linuxnode/gui/kivy/animations/composite.py
ebs/linuxnode/gui/kivy/background/__init__.py
ebs/linuxnode/gui/kivy/background/color.py
ebs/linuxnode/gui/kivy/background/image.py
ebs/linuxnode/gui/kivy/background/mixin.py
ebs/linuxnode/gui/kivy/background/overlay.py
ebs/linuxnode/gui/kivy/background/structured.py
ebs/linuxnode/gui/kivy/background/images/background.png
ebs/linuxnode/gui/kivy/core/__init__.py
ebs/linuxnode/gui/kivy/core/basemixin.py
ebs/linuxnode/gui/kivy/core/basenode.py
ebs/linuxnode/gui/kivy/core/busy.py
ebs/linuxnode/gui/kivy/core/display.py
ebs/linuxnode/gui/kivy/core/log.py
ebs/linuxnode/gui/kivy/core/nodeid.py
ebs/linuxnode/gui/kivy/core/structure.py
ebs/linuxnode/gui/kivy/core/text.py
ebs/linuxnode/gui/kivy/utils/__init__.py
ebs/linuxnode/gui/kivy/utils/application.py
ebs/linuxnode/gui/kivy/utils/keyboard.py
ebs/linuxnode/gui/kivy/utils/launcher.py
ebs_linuxnode_gui_kivy_core.egg-info/PKG-INFO
ebs_linuxnode_gui_kivy_core.egg-info/SOURCES.txt
ebs_linuxnode_gui_kivy_core.egg-info/dependency_links.txt
ebs_linuxnode_gui_kivy_core.egg-info/requires.txt
ebs_linuxnode_gui_kivy_core.egg-info/top_level.txt
example/app.py
example/image.jpg
example/node.py
example/run.py