Metadata-Version: 2.1
Name: ebs-linuxnode-gui-kivy-core
Version: 3.4.0
Summary: Kivy GUI Core for EBS Linuxnode Applications
Home-page: https://github.com/ebs-universe/ebs-linuxnode-coregui-kivy
Author: Chintalagiri Shashank
Author-email: shashank.chintalagiri@gmail.com
Classifier: Development Status :: 5 - Production/Stable
Classifier: Intended Audience :: Developers
Classifier: License :: OSI Approved :: GNU General Public License v3 or later (GPLv3+)
Classifier: Programming Language :: Python
Classifier: Programming Language :: Python :: 3
Classifier: Programming Language :: Python :: 3.6
Classifier: Operating System :: POSIX :: Linux
Requires-Dist: six
Requires-Dist: setuptools-scm
Requires-Dist: appdirs
Requires-Dist: kivy>=2.1.0
Requires-Dist: kivy-garden
Requires-Dist: kivy_garden.ebs.core>=1.3.0
Requires-Dist: kivy_garden.ebs.progressspinner>=1.2.0
Requires-Dist: ebs-linuxnode-core>=3.1.6
